classcharts/__init__.py
classcharts/homework/__init__.py
classcharts/homework/api.py
classcharts/homework/objects.py
classcharts/student/__init__.py
classcharts/student/api.py
classcharts/student/objects.py
classcharts/student/utils.py
classcharts.py-0.1.1.dist-info/LICENSE
classcharts.py-0.1.1.dist-info/METADATA
classcharts.py-0.1.1.dist-info/WHEEL
classcharts.py-0.1.1.dist-info/top_level.txt
classcharts.py-0.1.1.dist-info/RECORD
