Metadata-Version: 2.1
Name: classcharts.py
Version: 0.1.1
Summary: A python wrapper for the Classcharts API
Home-page: https://github.com/NCPlayz/classcharts.py
Author: NCPlayz
Author-email: chowdhurynadir0@outlook.com
License: MIT
Project-URL: Issue tracker, https://github.com/NCPlayz/classcharts.py/issues
Platform: UNKNOWN
Requires-Python: >=3.7.0
